Workbook

Sheet 0_guide
B1: mucho cuidado al copiar datos numericos con comas o puntos
A3: 1 | B3: our_id | C3: Identification number, the same as for the abstract screening
B4: study_type | C4: Categories: (1) remote sensing, (2) palaeoecology, (3) field study, (4) remote sensing and field study and (5) others
B5: study_level | C5: Categories: (1) comunity (focuses on community), (2) species (focuses on individual species) and (3) comunity and species (focuses on community level but also provides specific species measures, for example, pine density). Leave blank if the study does not focus on vegetation
B6: n_fires | C6: Number of fires analysed in the study
B7: revision_date | C7: date the article was reviewed
B8: comments | C8: Any additional relevant notes or observations
A10: 2 | B10: our_id | C10: Identification number, the same as for the abstract screening
B11: fire_id | C11: Identifier for each fire in the study, starting at 1 up to i
B12: fire_date | C12: Fire date in YYYY_MM_DD format. If specific details are missing, use YYYY_MM or YYYY. If the sampling period includes fires with unknown exact dates, record the full range (e.g., 1975-2001)
B13: season | C13: Record the season only if the date provides a year but no month, and explicitly includes a seasonal reference
B14: country | C14: Country or specific study site name
B15: origin_coords | C15: Source of study coordinates. Categories: (1) exact (explicitly stated in the text), (2) mean point (mean point of a range explicitly stated in the text, and, (3) estimated (not explicit; georeferenced based on site descriptions or location).
B16: latitude | C16: Latitude in decimal degrees (World Geodetic System 1984, EPSG: 4326). If there are several coordinates, enter the center point.
B17: longitude | C17: Longitude in decimal degrees (World Geodetic System 1984, EPSG: 4326). If there are several coordinates, enter the centre point.
B18: elevation | C18: Metres above sea level (m a.s.l.). If a range is given, enter the mean altitude. NA if not specified
B19: fire_size | C19: Affected area (ha). NA if not specified
B20: severity | C20: Categories: (1) low, (2) moderate, (3) high, (4) low;moderate, (5) moderate;high and, (6) all. Based on Keeley (2009). If fire severity is not explicitly stated but can be inferred from the description, classify it accordingly (e.g., active crown fire causing total tree mortality = high severity). If it cannot be determined, write NA.
B21: fire_type | C21: single / combined (If the results are given aggregated for many fires)
B22: forest_type | C22: Present prefire forest: Mixed, pine forest, oak forest, etc.
... B25: comments | C25: Any additional relevant notes or observations
A27: 3 | B27: our_id | C27: Identification number, the same as for the abstract screening
B28: response_variable | C28: Reported response variable in the study. Strictly post-fire only; exclude pre-fire measurements and results from unburned plots. Fire severity measurements are excluded because they characterize conditions during the fire event itself, not post-fire recovery responses. If a single response variable combines multiple measurements of the same property in the same units, report each measurement separately rather than aggregating them (e.g., report Na, K, and Ca content individually instead of as exchangeable cations). If a measure is expressed in different units for the same response variable, report both. If the response is adimensional, indicate the range of numerical variation from the reported results.
B29: response_units | C29: The unit in which the measured variable is reported. If its adimensional, report the range in which is measured.
B30: variable_type | C30: Categories: (1) vegetation, (2) soil (including microorganisms and fungii), (3) fauna and (4) others
B31: variable_subtype | C31: Specific classification of the response variable. Categories: (1) diversity, (2) composition, (3) structure and (4) regeneration, (5) physical properties, (6) chemical properties, (7) erosion, (8) interactions and (9) ecosystem services (Gann et al. 2019) (Wortley et al. 2013). Add more categories if necessary but report it in "Changes" shared document via Teams. Also, when it's a spectral response, report in "comments" the interpretation (for structure, composition, greeness, etc.). If you are unsure how to classify a variable, choose it based on the final purpose of the study; in other words, ask yourself what you intend to discover with that measurement.
B32: sampling_type | C32: Plot, transect, etc. For remote sensing, report whether the analysis is conducted at the pixel or plot level.
B33: measure_date | C33: First post-fire sampling date (YYYY_MM_DD). For remote sensing, use the earliest image acquisition date after the fire. Do not use pre-fire dates, even if reported in the study.
B34: season | C34: Record the season only if the date provides a year but no month, and explicitly includes a seasonal reference
B35: moderator_type | C35: Type of moderator variable tested as a potential source of variation in effect size (e.g., water stress, fire severity, years since fire, management, climate). Extract these when explicitly defined in methodology section and also reported in the results. Include variables treated as explanatory factors or predictors. Include predictors used in multivariate analyses (e.g., PCA, GLM). Exclude correlations without explanatory testing. Exclude random effects. Exclude interaction terms. When multiple moderators are reported, separate them with “;” (e.g., fire severity; management).
B36: comments | C36: Any additional relevant notes or observations
A38: 4 | B38: our_id | C38: Identification number, the same as for the abstract screening
B39: reason | C39: Reason for rejection
B40: comments | C40: Any additional relevant notes or observations

Sheet 1_study
A1: our_id | B1: study_type | C1: study_level | D1: n_fires | E1: revision_date | F1: comments | G1: Revisor
A2: 4 | B2: field;remote sensing | C2: community | D2: 1 | G2: Anna
A3: 16 | B3: remote sensing | C3: community | D3: 1 | G3: Anna
A4: 17 | B4: field | C4: community | D4: 1 | G4: Anna
A5: 29 | B5: field | C5: community | D5: 1 | G5: Anna
A6: 78 | B6: field | C6: community | D6: 1 | G6: Anna
A7: 84 | B7: field | C7: community | D7: 4 | G7: Anna
A8: 103 | B8: field | C8: community | D8: 1 | G8: Anna
A9: 111 | B9: field | C9: community | D9: 1 | G9: Anna
A10: 142 | B10: field | C10: community | D10: 2 | G10: Anna
A11: 145 | B11: field | C11: community | D11: 7 | G11: Anna
A12: 152 | B12: remote sensing | C12: community | D12: 2 | G12: Anna
A13: 168 | B13: remote sensing | C13: community | D13: 2 | G13: Anna
... A46: 523 | B46: field | C46: community | D46: 3 | G46: Anna
A47: 532 | B47: field;remote sensing | C47: community | D47: NA | G47: Anna
A48: 533 | B48: field | C48: community | D48: 9 | G48: Anna
A49: 550 | B49: field;remote sensing | C49: community | D49: 1 | G49: Anna
A50: 553 | B50: field | C50: community | D50: 5 | G50: Anna
A51: 561 | B51: field | C51: community | D51: 1 | G51: Anna
A52: 566 | B52: field | C52: community | D52: 1 | G52: Anna
A53: 597 | B53: palaeoecology | C53: species | D53: 2 | G53: Anna
A54: 603 | B54: field | C54: species | D54: 1 | G54: Anna
A55: 604 | B55: field | C55: community | D55: 2 | G55: Anna
A56: 612 | B56: palaeoecology | C56: community | D56: 22 | G56: Anna
A57: 617 | B57: remote sensing | C57: community | D57: NA | G57: Anna
A58: 621 | B58: field | C58: community | D58: 1 | G58: Anna
A59: 10 | B59: remote sensing | C59: community | D59: 1 | G59: Patri
A60: 12 | B60: field | C60: community | D60: 14 | G60: Patri
A61: 22 | B61: field | C61: community | D61: 1 | G61: Patri
A62: 32 | B62: field | C62: species | D62: 1 | G62: Patri
A63: 52 | B63: field | C63: species | D63: 5 | G63: Patri
A64: 65 | B64: palaeoecology | C64: species | D64: NA | G64: Patri
A65: 75 | B65: field | C65: species | D65: 2 | G65: Patri
A66: 631 | B66: field | C66: species | D66: 3 | G66: Anna
A67: 634 | B67: field | C67: community | D67: NA | G67: Anna
A68: 647 | B68: field | C68: community | D68: 1 | G68: Anna
A69: 674 | B69: field;remote sensing | C69: species | D69: 1 | G69: Anna
A70: 683 | B70: field | C70: community;species | D70: 2 | G70: Anna
A71: 687 | B71: field | C71: community;species | D71: NA | G71: Anna
A72: 708 | B72: field;remote sensing | C72: community | D72: 15 | G72: Anna
A73: 724 | B73: remote sensing | C73: community | D73: 473 | G73: Anna
A74: 738 | B74: field | C74: species | D74: 1 | G74: Anna
A75: 743 | B75: field | C75: species | D75: 1 | G75: Anna
A76: 753 | B76: field | C76: community | D76: 2 | G76: Anna
A77: 778 | B77: field;remote sensing | C77: community;species | D77: 1 | G77: Anna
A78: 788 | B78: field;remote sensing | C78: community | D78: 1 | G78: Anna
A79: 803 | B79: field | C79: community;species | D79: 1 | G79: Anna
A80: 811 | B80: field | C80: species | D80: 1 | G80: Anna
A81: 824 | B81: field | C81: species | D81: 1 | G81: Anna
A82: 833 | B82: remote sensing | C82: community | D82: NA | G82: Anna
A83: 841 | B83: field | C83: species | D83: 1 | G83: Anna
A84: 849 | B84: field | C84: community | D84: 1 | G84: Anna
A85: 854 | B85: remote sensing | C85: community | D85: 1 | G85: Anna
A86: 866 | B86: field | C86: community;species | D86: 1 | G86: Anna
A87: 868 | B87: field;remote sensing | C87: community | D87: 1 | G87: Anna
A88: 871 | B88: field;remote sensing | C88: community | D88: 1 | G88: Anna
A89: 874 | B89: remote sensing | C89: community | D89: 1 | G89: Anna
A90: 875 | B90: remote sensing | C90: community | D90: NA | G90: Anna
A91: 882 | B91: remote sensing | C91: community | D91: 6 | G91: Anna
A92: 885 | B92: remote sensing | C92: community | D92: 1 | G92: Anna
A93: 892 | B93: field | C93: species | D93: 1 | G93: Anna
A94: 904 | B94: field | C94: community;species | D94: 2 | G94: Anna
A95: 911 | B95: field | C95: community;species | D95: 1 | G95: Anna
A96: 913 | B96: field | C96: community;species | D96: 3 | G96: Anna
A97: 914 | B97: field;remote sensing | C97: community;species | D97: 6 | G97: Anna
A98: 916 | B98: field;remote sensing | C98: community;species | D98: 7156 | G98: Anna
A99: 934 | B99: field | C99: species | D99: 1 | G99: Anna
A100: 939 | B100: field | C100: community;species | D100: 1 | G100: Anna
A101: 992 | B101: field | C101: species | D101: 3 | G101: Anna
A102: 1008 | B102: field | C102: community;species | D102: 1 | G102: Anna
... A112: 218 | B112: field | C112: NA | D112: 2 | G112: Anna
A113: 220 | B113: field;remote sensing | C113: NA | D113: NA | G113: Anna
A114: 258 | B114: field | C114: NA | D114: 1 | G114: Anna
A115: 259 | B115: field | C115: NA | D115: 10 | G115: Anna
A116: 285 | B116: field | C116: NA | D116: 1 | G116: Anna
A117: 314 | B117: field | C117: NA | D117: 1 | G117: Anna
A118: 315 | B118: field;remote sensing | C118: NA | D118: 1 | G118: Anna
A119: 337 | B119: field | C119: NA | D119: 1 | G119: Anna
A120: 388 | B120: field;remote sensing | C120: NA | D120: 1 | G120: Anna
A121: 399 | B121: field | C121: NA | D121: 1 | G121: Anna
A122: 752 | B122: field | C122: species | D122: 4 | E122: 2026_04_27 | G122: Anna
A123: 74 | B123: field | C123: species | D123: 3 | E123: 2026_04_27 | G123: Anna | H123: *se lo pase cuando iba por aqui
A124: 69 | B124: field | C124: community | D124: 1 | E124: 2026_05_02 | G124: Anna
A125: 463 | B125: field | C125: NA | D125: NA | E125: 2026_05_04 | G125: Anna
A126: 555 | B126: remote sensing | C126: community | D126: 1 | E126: 2026_05_04 | G126: Anna
A127: 905 | B127: remote sensing | C127: community | D127: NA | E127: 2026_05_04 | G127: Anna
A128: 362 | B128: field | C128: NA | D128: 4 | E128: 2026_05_04 | G128: Anna
A129: 526 | B129: field | C129: NA | D129: 4 | E129: 2026_05_06 | G129: Anna
A130: 956 | B130: field | C130: NA | D130: NA | E130: 2026_05_06 | G130: Anna
A131: 309 | B131: remote sensing | C131: community | D131: 1 | E131: 2026_05_06 | G131: Anna
A132: 236 | B132: field;remote sensing | C132: NA | D132: 2 | E132: 2026_05_07 | G132: Anna
A133: 972 | B133: field | C133: community;species | D133: 1 | E133: 2026_05_07 | G133: Anna
A134: 212 | B134: remote sensing | C134: community | D134: NA | E134: 2026_05_07 | G134: Anna
A135: 785 | B135: remote sensing | C135: NA | D135: 2 | E135: 2026_05_07 | G135: Anna
A136: 814 | B136: field;remote sensing | C136: NA | D136: 1 | E136: 2026_05_07 | G136: Anna
A137: 581 | B137: field | C137: NA | D137: 1 | E137: 2026_05_07 | G137: Anna
A138: 452 | B138: field | C138: community | D138: 1 | E138: 28_04_2026 | G138: Sofia
A139: 465 | B139: remote sensing | C139: community | D139: 6 | E139: 28_04_2026 | G139: Sofia
A140: 496 | B140: field | C140: community | D140: 2 | E140: 29_04_2026 | G140: Sofia
A141: 508 | B141: field | C141: community | D141: 1 | E141: 29_04_2026 | G141: Sofia
...

Sheet 1_study_resumen
A1: tipo estudio | B1: recuento
A2: field | B2: =COUNTIF('1_study'!B2:B288, "field") -> 211 | E2: me quedo con las 3
A3: remote sensing | B3: =COUNTIF('1_study'!B3:B288, "remote sensing") -> 33
A4: field;remote sensing | B4: =COUNTIF('1_study'!B4:B288, "field;remote sensing") -> 39
A5: palaeoecology | B5: =COUNTIF('1_study'!B5:B288, "palaeoecology") -> 3
B6: =SUM(B2:B5) -> 286
L10: ST
K11: SL | L11: field | M11: rs | N11: field;rs | Q11: total estudios | R11: =SUM(B2:B4) -> 283
K12: comm | L12: 32 | M12: 22 | N12: 13
K13: comm;sp | L13: 12 | M13: 0 | N13: 3
K14: sp | L14: 23 | M14: 0 | N14: 2
I17: % global | K17: Tipo de estudio | O17: Nivel de estudio | P17: Tipo de estudio
J18: Nivel de estudio | K18: Campo | L18: Teledetección | M18: Campo + Teledetección | P18: Campo | Q18: Teledetección | R18: Campo + Teledetección | S18: Paleoecología
J19: Comunidad | K19: 31.85 | L19: 17.04 | M19: 10.37 | O19: Comunidad | P19: 31.85 | Q19: 17.04 | R19: 10.37
J20: Comunidad + Especies | K20: 14.07 | L20: 0.74 | M20: 2.2 | O20: Comunidad + Especies | P20: 14.07 | Q20: 0.74 | R20: 2.2
J21: Especies | K21: 21.48 | L21: 0 | M21: 2.2 | O21: Especies | P21: 21.48 | Q21: 0 | R21: 2.2
I23: % portipoestudio | K23: Tipo de estudio
J24: Nivel de estudio | K24: Campo | L24: Teledetección | M24: Campo + Teledetección
J25: Comunidad | K25: 47.761194 | L25: 100 | M25: 72.222222
J26: Comunidad + Especies | K26: 17.910448 | L26: 0 | M26: 16.666667
J27: Especies | K27: 34.328358 | L27: 0 | M27: 11.111111 | O27: study_type
O28: study_level field field;remote sensing palaeoecology remote sensing
O29: community 27.8026906 8.9686099 0.4484305 13.0044843
A30: study_type | B30: study_level | C30: n_fires | O30: community;species 19.7309417 4.0358744 0.0000000 0.4484305
A31: remote sensing | B31: community | C31: 1 | O31: species 23.7668161 0.8968610 0.8968610 0.0000000
A32: remote sensing | B32: community | C32: 2 | E32: =AVERAGE(C31:C38,C41,C44:C45,C47:C49,C51,C53:C57,C59:C63) -> 2.2
A33: remote sensing | B33: community | C33: 2 | E33: =AVERAGE(C31:C39,C41:C42,C44:C45,C47:C49,C51,C53:C57,C59:C63) -> 172.55556 | J33: study_type
A34: remote sensing | B34: community | C34: 1 | J34: study_level field remote sensing field;remote sensing
A35: remote sensing | B35: community | C35: 3 | J35: community 31.8518519 17.0370370 10.3703704
A36: remote sensing | B36: community | C36: 2 | J36: community;species 14.0740741 0.7407407 2.2222222
A37: remote sensing | B37: community | C37: 2 | J37: species 21.4814815 0.0000000 2.2222222
A38: remote sensing | B38: community | C38: 1
A39: remote sensing | B39: community | C39: 4131
A40: remote sensing | B40: community | C40: NA
A41: remote sensing | B41: community | C41: 1
A42: remote sensing | B42: community | C42: 473
A43: remote sensing | B43: community | C43: NA
A44: remote sensing | B44: community | C44: 1
A45: remote sensing | B45: community | C45: 1
A46: remote sensing | B46: community | C46: NA
A47: remote sensing | B47: community | C47: 6
A48: remote sensing | B48: community | C48: 1
A49: remote sensing | B49: community | C49: 1
A50: remote sensing | B50: community | C50: NA
A51: remote sensing | B51: community | C51: 1
A52: remote sensing | B52: community | C52: NA
A53: remote sensing | B53: NA | C53: 2
A54: remote sensing | B54: community | C54: 6
A55: remote sensing | B55: community;species | C55: 4
A56: remote sensing | B56: community | C56: 1
A57: remote sensing | B57: community | C57: 1
A58: remote sensing | B58: community | C58: NA
A59: remote sensing | B59: NA | C59: 5
A60: remote sensing | B60: community | C60: 6
A61: remote sensing | B61: NA | C61: 1
A62: remote sensing | B62: community | C62: 1
A63: remote sensing | B63: community | C63: 2

Sheet 2_fire
A1: our_id | B1: fire_id | C1: fire_date | D1: season | E1: country | F1: origin_coords | G1: latitude | H1: longitude | I1: elevation | J1: fire_size | K1: severity | L1: fire_type | M1: forest_type | N1: forest_details | O1: postfire_management | P1: comments
A2: 4 | B2: 1 | C2: 2016_01_06 | D2: summer | E2: Australia | F2: exact | G2: -32.15 | H2: 116.8 | I2: 248 | J2: 69165 | K2: high | L2: single | M2: eucalypt forest | N2: dry sclerophyll forest domi-nated by Eucalyptus marginata | O2: none
A3: 16 | B3: 1 | C3: 2017_10_15 | D3: autumn | E3: Portugal | F3: mean point | G3: 40.333333 | H3: -7.85 | I3: 400 | J3: 7600 | K3: high | L3: single | M3: pine forest | N3: dominated by Pinus pinaster | O3: none
A4: 16 | B4: 1 | C4: 2017_10_15 | D4: autumn | E4: Portugal | F4: mean point | G4: 40.333333 | H4: -7.85 | I4: 400 | J4: 7600 | K4: high | L4: single | M4: broadleaves forest | N4: The forest is mainly composed of pine trees (43%) and broadleaf trees (13%). Pinus pinaster is cultivated. There is Eucalyptus globulus as exotic specie that is 1% of the area. On the other hand, invasive forest species, like Acacia dealbata and Ailanthus altissima, occupy 10% of the area | O4: none
A5: 17 | B5: 1 | C5: 2015_09_12 | D5: summer | E5: EEUU | F5: exact | G5: 38.83528 | H5: -122.70148 | I5: =(1050+1113)/2 -> 1081.5 | J5: 30700 | K5: high | L5: single | M5: pine forest | N5: dominated by Pinus ponderosa | O5: erosion control
A6: 17 | B6: 1 | C6: 2015_09_12 | D6: summer | E6: EEUU | F6: exact | G6: 38.83528 | H6: -122.70148 | I6: =(1050+1113)/2 -> 1081.5 | J6: 30700 | K6: high | L6: single | M6: pine forest | N6: dominated by Pinus ponderosa | O6: silvicultural
A7: 29 | B7: 1 | C7: 1994_07_05 | D7: summer | E7: Spain | F7: estimated | G7: 41.773889 | H7: 2.9280556 | I7: =(190+250)/2 -> 220 | J7: 55 | K7: NA | L7: single | M7: pine forest | N7: dominated by Pinus pinaster | O7: erosion control
A8: 29 | B8: 1 | C8: 1994_07_05 | D8: summer | E8: Spain | F8: estimated | G8: 41.773889 | H8: 2.9280556 | I8: =(190+250)/2 -> 220 | J8: 55 | K8: NA | L8: single | M8: cork oak forest | N8: dominated by Quercus suber | O8: erosion control
A9: 29 | B9: 1 | C9: 1994_07_05 | D9: summer | E9: Spain | F9: estimated | G9: 41.773889 | H9: 2.9280556 | I9: =(190+250)/2 -> 220 | J9: 55 | K9: NA | L9: single | M9: pine forest | N9: dominated by Pinus pinaster | O9: reforestation
A10: 29 | B10: 1 | C10: 1994_07_05 | D10: summer | E10: Spain | F10: estimated | G10: 41.773889 | H10: 2.9280556 | I10: =(190+250)/2 -> 220 | J10: 55 | K10: NA | L10: single | M10: cork oak forest | N10: dominated by Quercus suber | O10: reforestation
A11: 78 | B11: 1 | C11: 1989_08 | D11: summer | E11: Greece | F11: mean point | G11: 40.08 | H11: 23.8 | I11: NA | J11: NA | K11: NA | L11: single | M11: pine forest | N11: dominated by Pinus halepensis | O11: none
A12: 84 | B12: 1 | C12: 1978 | E12: Spain | F12: exact | G12: 39.318 | H12: -0.8947 | I12: =(420+400+610+450+475)/5 -> 471 | J12: >500 | K12: NA | L12: combined | M12: pine forest | N12: dominated by Pinus halepensis | O12: none | P12: origin of coordinates is in a supplementary table, out of the article
A13: 84 | B13: 2 | C13: 1979 | E13: Spain | F13: exact | G13: 38.913 | H13: -0.817 | I13: =(806+800+530+806)/4 -> 735.5 | J13: >500 | K13: NA | L13: combined | M13: pine forest | N13: dominated by Pinus halepensis | O13: none | P13: origin of coordinates is in a supplementary table, out of the article
A14: 84 | B14: 3 | C14: 1979 | E14: Spain | F14: exact | G14: 38.803611 | H14: -0.56777778 | I14: 630 | J14: >500 | K14: NA | L14: combined | M14: pine forest | N14: dominated by Pinus halepensis | O14: none | P14: origin of coordinates is in a supplementary table, out of the article
A15: 84 | B15: 4 | C15: 1981 | E15: Spain | F15: exact | G15: 38.803611 | H15: -0.56777778 | I15: 630 | J15: >500 | K15: NA | L15: combined | M15: pine forest | N15: dominated by Pinus halepensis | O15: none | P15: origin of coordinates is in a supplementary table, out of the article
A16: 84 | B16: 5 | C16: 1984 | E16: Spain | F16: exact | G16: 38.913 | H16: -0.817 | I16: =(806+800+530+806)/4 -> 735.5 | J16: >500 | K16: NA | L16: combined | M16: pine forest | N16: dominated by Pinus halepensis | O16: none | P16: origin of coordinates is in a supplementary table, out of the article
A17: 84 | B17: 6 | C17: 1985 | E17: Spain | F17: exact | G17: 38.913 | H17: -0.817 | I17: =(806+800+530+806)/4 -> 735.5 | J17: >500 | K17: NA | L17: combined | M17: pine forest | N17: dominated by Pinus halepensis | O17: none | P17: origin of coordinates is in a supplementary table, out of the article
A18: 84 | B18: 7 | C18: 1991 | E18: Spain | F18: exact | G18: 38.675 | H18: -0.09104 | I18: =(340+445+300+415)/4 -> 375 | J18: >500 | K18: NA | L18: combined | M18: pine forest | N18: dominated by Pinus halepensis | O18: none | P18: origin of coordinates is in a supplementary table, out of the article
A19: 84 | B19: 8 | C19: 1991 | E19: Spain | F19: exact | G19: 39.318 | H19: -0.8947 | I19: =(420+400+610+450+475)/5 -> 471 | J19: >500 | K19: NA | L19: combined | M19: pine forest | N19: dominated by Pinus halepensis | O19: none | P19: origin of coordinates is in a supplementary table, out of the article
A20: 84 | B20: 9 | C20: 1994 | E20: Spain | F20: exact | G20: 38.913 | H20: -0.817 | I20: =(806+800+530+806)/4 -> 735.5 | J20: >500 | K20: NA | L20: combined | M20: pine forest | N20: dominated by Pinus halepensis | O20: none | P20: origin of coordinates is in a supplementary table, out of the article
A21: 84 | B21: 10 | C21: 1994 | E21: Spain | F21: exact | G21: 38.803611 | H21: -0.56777778 | I21: 630 | J21: >500 | K21: NA | L21: combined | M21: pine forest | N21: dominated by Pinus halepensis | O21: none | P21: origin of coordinates is in a supplementary table, out of the article
A22: 84 | B22: 11 | C22: 1999 | E22: Spain | F22: exact | G22: 38.913 | H22: -0.817 | I22: =(806+800+530+806)/4 -> 735.5 | J22: >500 | K22: NA | L22: combined | M22: pine forest | N22: dominated by Pinus halepensis | O22: none | P22: origin of coordinates is in a supplementary table, out of the article
A23: 84 | B23: 12 | C23: 2003 | E23: Spain | F23: exact | G23: 38.675 | H23: -0.09104 | I23: =(340+445+300+415)/4 -> 375 | J23: >500 | K23: NA | L23: combined | M23: pine forest | N23: dominated by Pinus halepensis | O23: none | P23: origin of coordinates is in a supplementary table, out of the article
A24: 84 | B24: 13 | C24: 2010 | E24: Spain | F24: exact | G24: 38.803611 | H24: -0.56777778 | I24: 630 | J24: >500 | K24: NA | L24: combined | M24: pine forest | N24: dominated by Pinus halepensis | O24: none | P24: origin of coordinates is in a supplementary table, out of the article
A25: 84 | B25: 14 | C25: 2012 | E25: Spain | F25: exact | G25: 39.318 | H25: -0.8947 | I25: =(420+400+610+450+475)/5 -> 471 | J25: >500 | K25: NA | L25: combined | M25: pine forest | N25: dominated by Pinus halepensis | O25: none | P25: origin of coordinates is in a supplementary table, out of the article
A26: 84 | B26: 15 | C26: 2016 | E26: Spain | F26: exact | G26: 38.675 | H26: -0.09104 | I26: =(340+445+300+415)/4 -> 375 | J26: >500 | K26: NA | L26: combined | M26: pine forest | N26: dominated by Pinus halepensis | O26: none | P26: origin of coordinates is in a supplementary table, out of the article
A27: 103 | B27: 1 | C27: 2005_09 | E27: Spain | F27: mean point | G27: 36.953333 | H27: -3.4933333 | I27: =(1477+2053)/2 -> 1765 | J27: 1300 | K27: high | L27: single | M27: pine forest | N27: P. pinaster, P. nigra, P. sylvestris in order of increasing elevation | O27: silvicultural
A28: 111 | B28: 1 | C28: 2012_07 | D28: summer | E28: Spain | F28: estimated | G28: 38.393 | H28: -1.682 | I28: 500 | J28: 6500 | K28: high | L28: single | M28: pine forest | N28: dominated by Pinus halepensis | O28: erosion control
A29: 142 | B29: 1 | C29: 1994 | D29: summer | E29: Spain | F29: exact | G29: 38.333333 | H29: -2.3333333 | I29: 1010 | J29: 14000 | K29: NA | L29: single | M29: pine forest | N29: dominated by Pinus halepensis | O29: silvicultural;erosion control
A30: 142 | B30: 2 | C30: 1994 | D30: summer | E30: Spain | F30: exact | G30: 38.266667 | H30: -1.6333333 | I30: 325 | J30: 30000 | K30: NA | L30: single | M30: pine forest | N30: dominated by Pinus halepensis | O30: silvicultural;erosion control
A31: 145 | B31: 1 | C31: 1979 | E31: Turkey | F31: mean point | G31: 36.9 | H31: 28.1 | I31: 101 | J31: NA | K31: NA | L31: combined | M31: pine forest | N31: dominated by Pinus brutia | O31: none
A32: 145 | B32: 2 | C32: 1989 | E32: Turkey | F32: mean point | G32: 36.9 | H32: 28.1 | I32: 101 | J32: NA | K32: NA | L32: combined | M32: pine forest | N32: dominated by Pinus brutia | O32: none
A33: 145 | B33: 3 | C33: 1995 | E33: Turkey | F33: mean point | G33: 36.9 | H33: 28.1 | I33: 101 | J33: NA | K33: NA | L33: combined | M33: pine forest | N33: dominated by Pinus brutia | O33: none
A34: 145 | B34: 4 | C34: 1996 | E34: Turkey | F34: mean point | G34: 36.9 | H34: 28.1 | I34: 101 | J34: NA | K34: NA | L34: combined | M34: pine forest | N34: dominated by Pinus brutia | O34: none
A35: 145 | B35: 5 | C35: 1997 | E35: Turkey | F35: mean point | G35: 36.9 | H35: 28.1 | I35: 101 | J35: NA | K35: NA | L35: combined | M35: pine forest | N35: dominated by Pinus brutia | O35: none
A36: 145 | B36: 6 | C36: 1999 | E36: Turkey | F36: mean point | G36: 36.9 | H36: 28.1 | I36: 101 | J36: NA | K36: NA | L36: combined | M36: pine forest | N36: dominated by Pinus brutia | O36: none
A37: 145 | B37: 7 | C37: 2002 | E37: Turkey | F37: mean point | G37: 36.9 | H37: 28.1 | I37: 101 | J37: NA | K37: NA | L37: combined | M37: pine forest | N37: dominated by Pinus brutia | O37: none
A38: 152 | B38: 1 | C38: 1966_08 | D38: summer | E38: Spain | F38: estimated | G38: 40.460933 | H38: -4.269 | I38: 800 | J38: 790 | K38: NA | L38: single | M38: pine forest | N38: dominated by Pinus pinaster | O38: reforestation
A39: 152 | B39: 2 | C39: 1999_08 | D39: summer | E39: Spain | F39: estimated | G39: 40.620678 | H39: -4.152 | I39: 1340 | J39: 425 | K39: NA | L39: single | M39: pine forest | N39: dominated by Pinus sylvestris | O39: reforestation
A40: 168 | B40: 1 | C40: 2000 | E40: Algeria | F40: mean point | G40: 36.3867 | H40: 0.966 | I40: =(13+867)/2 -> 440 | J40: 5000 | K40: low | L40: single | M40: pine forest | N40: dominated by Pinus halepensis | O40: none
A41: 168 | B41: 2 | C41: 2012 | E41: Algeria | F41: mean point | G41: 36.3867 | H41: 0.966 | I41: =(13+867)/2 -> 440 | J41: 6000 | K41: high | L41: single | M41: pine forest | N41: dominated by Pinus halepensis | O41: none
A42: 177 | B42: 1 | C42: 1989_09 | E42: Israel | F42: exact | G42: 32.733333 | H42: 35.016667 | I42: 320 | J42: 300 | K42: NA | L42: single | M42: pine forest | N42: dominated by Pinus halepensis | O42: silvicultural
A43: 187 | B43: 1 | C43: 1989_09_19 | D43: summer | E43: Israel | F43: mean point | G43: 32.73696 | H43: 35.036 | I43: 700 | J43: 400 | K43: high | L43: single | M43: sclerophyll forest | N43: dominated by Pinus halepensis | O43: reforestation
A44: 190 | B44: 1 | C44: 1984 | E44: Spain | F44: mean point | G44: 38.7144 | H44: 0.1772 | I44: NA | J44: NA | K44: NA | L44: combined | M44: oak forest | N44: dominated by Holm Oaks | O44: none
A45: 190 | B45: 2 | C45: 1985 | E45: Spain | F45: mean point | G45: 38.7144 | H45: 0.1772 | I45: NA | J45: NA | K45: NA | L45: combined | M45: oak forest | N45: dominated by Holm Oaks | O45: none
A46: 200 | B46: 1 | C46: 1994_08 | D46: summer | E46: Spain | F46: exact | G46: 38.366667 | H46: -2.4 | I46: 900 | J46: 14000 | K46: NA | L46: single | M46: pine forest | N46: dominated by Pinus halepensis | O46: silvicultural
A47: 208 | B47: 1 | C47: 1979 | E47: Spain | F47: estimated | G47: 38.134 | H47: -1.4279 | I47: =(500+1000)/2 -> 750 | J47: 30 | K47: NA | L47: single | M47: pine forest | N47: dominated by Pinus halepensis | O47: none
A48: 208 | B48: 2 | C48: 1994 | E48: Spain | F48: estimated | G48: 38.134 | H48: -1.4279 | I48: =(500+1000)/2 -> 750 | J48: 50 | K48: NA | L48: single | M48: pine forest | N48: dominated by Pinus halepensis | O48: none
A49: 208 | B49: 3 | C49: 2000 | E49: Spain | F49: estimated | G49: 38.134 | H49: -1.4279 | I49: =(500+1000)/2 -> 750 | J49: 60 | K49: NA | L49: single | M49: pine forest | N49: dominated by Pinus halepensis | O49: none
A50: 209 | B50: 1 | C50: 2004_09 | E50: Spain | F50: exact | G50: 42.05 | H50: 3.1166667 | I50: NA | J50: 627 | K50: high | L50: single | M50: pine forest | N50: dominated by Pinus halepensis | O50: silvicultural;erosion control
A51: 215 | B51: 1 | C51: 1986 | E51: Spain | F51: estimated | G51: 38.0144 | H51: -2.87275 | I51: NA | J51: NA | K51: NA | L51: single | M51: pine forest | N51: dominated by Pinus nigra, Pinus pinaster, and Pinus halepensis | O51: reforestation
A52: 215 | B52: 2 | C52: 2001 | E52: Spain | F52: estimated | G52: 37.9468 | H52: -2.941 | I52: NA | J52: NA | K52: NA | L52: single | M52: pine forest | N52: dominated by Pinus nigra, Pinus pinaster, and Pinus halepensis | O52: reforestation
A53: 222 | B53: 1 | C53: 1989_09_19 | D53: summer | E53: Israel | F53: mean point | G53: 32.7555 | H53: 35.021 | I53: 500 | J53: 530 | K53: NA | L53: single | M53: sclerophyll forest | N53: Pinus halepensis–Pistacia palestina-Cistus sp. associations on south facing slopes and Quarcus calliprinos - Pistacia palastina association on north facing slopes | O53: none
A54: 222 | B54: 2 | C54: 1998_10_11 | D54: autumn | E54: Israel | F54: mean point | G54: 32.7555 | H54: 35.021 | I54: 500 | J54: 161 | K54: NA | L54: single | M54: sclerophyll forest | N54: Pinus halepensis–Pistacia palestina-Cistus sp. associations on south facing slopes and Quarcus calliprinos - Pistacia palastina association on north facing slopes | O54: none
A55: 222 | B55: 3 | C55: 1999_12_04 | D55: autumn | E55: Israel | F55: mean point | G55: 32.7555 | H55: 35.021 | I55: 500 | J55: 158 | K55: NA | L55: single | M55: sclerophyll forest | N55: Pinus halepensis–Pistacia palestina-Cistus sp. associations on south facing slopes and Quarcus calliprinos - Pistacia palastina association on north facing slopes | O55: none
A56: 240 | B56: 1 | C56: 2017_07 | D56: summer | E56: Italy | F56: mean point | G56: 40.8125 | H56: 14.413611 | I56: NA | J56: NA | K56: high | L56: single | M56: pine forest | N56: dominated by Pinus pinaster | O56: none
A57: 245 | B57: 1 | C57: 2003_09_11 | D57: summer | E57: Portugal | F57: exact | G57: 38.975 | H57: -9.2644444 | I57: =(100+350)/2 -> 225 | J57: 570 | K57: high | L57: single | M57: broadleaves forest;coniferous forests | N57: dominant species include Quercus faginea, Quercus suber, Quercus coccifera, Pinus pinaster and Pinus pinea | O57: silvicultural
A58: 266 | B58: 1 | C58: 1993 | E58: Spain | F58: estimated | G58: 39.39 | H58: -0.9377 | I58: NA | J58: 26000 | K58: NA | L58: combined | M58: pine forest | N58: dominated by Pinus halepensis | O58: none
A59: 266 | B59: 2 | C59: 1994 | E59: Spain | F59: estimated | G59: 39.39 | H59: -0.9377 | I59: NA | J59: 140000 | K59: high | L59: combined | M59: pine forest | N59: dominated by Pinus halepensis | O59: none
A60: 270 | B60: 1 | C60: 1982 | E60: Spain | F60: estimated | G60: 41.6177 | H60: 1.75999 | I60: 259 | J60: 205 | K60: NA | L60: combined | M60: pine forest | N60: dominated by Pinus halepensis | O60: none
A61: 270 | B61: 2 | C61: 1982 | E61: Spain | F61: estimated | G61: 41.6177 | H61: 1.75999 | I61: 225 | J61: 96 | K61: NA | L61: combined | M61: pine forest | N61: dominated by Pinus halepensis | O61: none
A62: 270 | B62: 3 | C62: 1991 | E62: Spain | F62: estimated | G62: 41.6177 | H62: 1.75999 | I62: 177 | J62: 257 | K62: NA | L62: combined | M62: pine forest | N62: dominated by Pinus halepensis | O62: none
A63: 270 | B63: 4 | C63: 1986 | E63: Spain | F63: estimated | G63: 41.6177 | H63: 1.75999 | I63: 275 | J63: 48 | K63: NA | L63: combined | M63: pine forest | N63: dominated by Pinus halepensis | O63: none
A64: 270 | B64: 5 | C64: 1986_08_18 | D64: summer | E64: Spain | F64: estimated | G64: 41.6177 | H64: 1.75999 | I64: 192 | J64: 1335 | K64: NA | L64: combined | M64: pine forest | N64: dominated by Pinus halepensis | O64: none
A65: 270 | B65: 6 | C65: 1978 | E65: Spain | F65: estimated | G65: 41.6177 | H65: 1.75999 | I65: 555 | J65: 140 | K65: NA | L65: combined | M65: pine forest | N65: dominated by Pinus halepensis | O65: none
A66: 270 | B66: 7 | C66: 1989_07_15 | D66: summer | E66: Spain | F66: estimated | G66: 41.6177 | H66: 1.75999 | I66: 400 | J66: 334 | K66: NA | L66: combined | M66: pine forest | N66: dominated by Pinus halepensis | O66: none
A67: 270 | B67: 8 | C67: 1985_07_25 | D67: summer | E67: Spain | F67: estimated | G67: 41.6177 | H67: 1.75999 | I67: 460 | J67: 980 | K67: NA | L67: combined | M67: pine forest | N67: dominated by Pinus halepensis | O67: none
A68: 270 | B68: 9 | C68: 1979_09_02 | D68: summer | E68: Spain | F68: estimated | G68: 41.6177 | H68: 1.75999 | I68: 758 | J68: 54 | K68: NA | L68: combined | M68: pine forest | N68: dominated by Pinus halepensis | O68: none
A69: 270 | B69: 10 | C69: 1981 | E69: Spain | F69: estimated | G69: 41.6177 | H69: 1.75999 | I69: 651 | J69: 3176 | K69: NA | L69: combined | M69: pine forest | N69: dominated by Pinus halepensis | O69: none
A70: 270 | B70: 11 | C70: 1983_06_14 | D70: spring | E70: Spain | F70: estimated | G70: 41.6177 | H70: 1.75999 | I70: 317 | J70: 137 | K70: NA | L70: combined | M70: pine forest | N70: dominated by Pinus halepensis | O70: none
A71: 270 | B71: 12 | C71: 1983_10_17 | D71: autumn | E71: Spain | F71: estimated | G71: 41.6177 | H71: 1.75999 | I71: 606 | J71: 120 | K71: NA | L71: combined | M71: pine forest | N71: dominated by Pinus halepensis | O71: none
A72: 270 | B72: 13 | C72: 1983_08_01 | D72: summer | E72: Spain | F72: estimated | G72: 41.6177 | H72: 1.75999 | I72: 469 | J72: 1078 | K72: NA | L72: combined | M72: pine forest | N72: dominated by Pinus halepensis | O72: none
A73: 270 | B73: 14 | C73: 1983_07_28 | D73: summer | E73: Spain | F73: estimated | G73: 41.6177 | H73: 1.75999 | I73: 419 | J73: 619 | K73: NA | L73: combined | M73: pine forest | N73: dominated by Pinus halepensis | O73: none
A74: 270 | B74: 15 | C74: 1994_07_04 | D74: summer | E74: Spain | F74: estimated | G74: 41.6177 | H74: 1.75999 | I74: 234 | J74: 1890 | K74: NA | L74: combined | M74: pine forest | N74: dominated by Pinus halepensis | O74: none
A75: 270 | B75: 16 | C75: 1994_08_10 | D75: summer | E75: Spain | F75: estimated | G75: 41.6177 | H75: 1.75999 | I75: 502 | J75: 406 | K75: NA | L75: combined | M75: pine forest | N75: dominated by Pinus halepensis | O75: none
A76: 270 | B76: 17 | C76: 1994_04_07 | D76: spring | E76: Spain | F76: estimated | G76: 41.6177 | H76: 1.75999 | I76: 412 | J76: 70 | K76: NA | L76: combined | M76: pine forest | N76: dominated by Pinus halepensis | O76: none
A77: 270 | B77: 18 | C77: 1994_07_02 | D77: summer | E77: Spain | F77: estimated | G77: 41.6177 | H77: 1.75999 | I77: 460 | J77: 83 | K77: NA | L77: combined | M77: pine forest | N77: dominated by Pinus halepensis | O77: none
A78: 270 | B78: 19 | C78: 1994_07_20 | D78: summer | E78: Spain | F78: estimated | G78: 41.6177 | H78: 1.75999 | I78: 740 | J78: 159 | K78: NA | L78: combined | M78: pine forest | N78: dominated by Pinus halepensis | O78: none
A79: 270 | B79: 20 | C79: 1994_04_10 | D79: spring | E79: Spain | F79: estimated | G79: 41.6177 | H79: 1.75999 | I79: 632 | J79: 1310 | K79: NA | L79: combined | M79: pine forest | N79: dominated by Pinus halepensis | O79: none
A80: 270 | B80: 21 | C80: 1994_04_02 | D80: spring | E80: Spain | F80: estimated | G80: 41.6177 | H80: 1.75999 | I80: 289 | J80: 1360 | K80: NA | L80: combined | M80: pine forest | N80: dominated by Pinus halepensis | O80: none
A81: 270 | B81: 22 | C81: 1994_07_04 | D81: summer | E81: Spain | F81: estimated | G81: 41.6177 | H81: 1.75999 | I81: 437 | J81: 38976 | K81: NA | L81: combined | M81: pine forest | N81: dominated by Pinus halepensis | O81: none
A82: 271 | B82: 1 | C82: 1981 | E82: Spain | F82: mean point | G82: 41.598 | H82: 1.493 | I82: NA | J82: NA | K82: NA | L82: single | M82: pine forest | N82: dominated by Pinus halepensis | O82: silvicultural
A83: 271 | B83: 2 | C83: 1985 | E83: Spain | F83: mean point | G83: 41.659 | H83: 1.62096 | I83: NA | J83: NA | K83: NA | L83: single | M83: pine forest | N83: dominated by Pinus halepensis | O83: silvicultural
A84: 271 | B84: 3 | C84: 1993 | E84: Spain | F84: mean point | G84: 41.7735 | H84: 1.71 | I84: NA | J84: NA | K84: NA | L84: single | M84: pine forest | N84: dominated by Pinus halepensis | O84: silvicultural
A85: 280 | B85: 1 | C85: 1959 | E85: France | F85: exact | G85: 43.280796 | H85: 6.387 | I85: NA | J85: NA | K85: NA | L85: combined | M85: pine forest;oak forest | N85: dominated by pine (P. pinaster) and oak (Q. suber, Q. ilex and Q. pubescens) | O85: none
A86: 280 | B86: 2 | C86: 1959 | E86: France | F86: exact | G86: 43.280796 | H86: 6.387 | I86: NA | J86: NA | K86: NA | L86: combined | M86: pine forest;oak forest | N86: dominated by pine (P. pinaster) and oak (Q. suber, Q. ilex and Q. pubescens) | O86: none
A87: 280 | B87: 3 | C87: 1959 | E87: France | F87: exact | G87: 43.280796 | H87: 6.387 | I87: NA | J87: NA | K87: NA | L87: combined | M87: pine forest;oak forest | N87: dominated by pine (P. pinaster) and oak (Q. suber, Q. ilex and Q. pubescens) | O87: none
A88: 280 | B88: 4 | C88: 1959 | E88: France | F88: exact | G88: 43.280796 | H88: 6.387 | I88: NA | J88: NA | K88: NA | L88: combined | M88: pine forest;oak forest | N88: dominated by pine (P. pinaster) and oak (Q. suber, Q. ilex and Q. pubescens) | O88: none
A89: 280 | B89: 5 | C89: 1959 | E89: France | F89: exact | G89: 43.280796 | H89: 6.387 | I89: NA | J89: NA | K89: NA | L89: combined | M89: pine forest;oak forest | N89: dominated by pine (P. pinaster) and oak (Q. suber, Q. ilex and Q. pubescens) | O89: none
A90: 280 | B90: 6 | C90: 1959 | E90: France | F90: exact | G90: 43.280796 | H90: 6.387 | I90: NA | J90: NA | K90: NA | L90: combined | M90: pine forest;oak forest | N90: dominated by pine (P. pinaster) and oak (Q. suber, Q. ilex and Q. pubescens) | O90: none
A91: 280 | B91: 7 | C91: 1959 | E91: France | F91: exact | G91: 43.280796 | H91: 6.387 | I91: NA | J91: NA | K91: NA | L91: combined | M91: pine forest;oak forest | N91: dominated by pine (P. pinaster) and oak (Q. suber, Q. ilex and Q. pubescens) | O91: none
A92: 280 | B92: 8 | C92: 1959 | E92: France | F92: exact | G92: 43.280796 | H92: 6.387 | I92: NA | J92: NA | K92: NA | L92: combined | M92: pine forest;oak forest | N92: dominated by pine (P. pinaster) and oak (Q. suber, Q. ilex and Q. pubescens) | O92: none
A93: 280 | B93: 9 | C93: 1959 | E93: France | F93: exact | G93: 43.280796 | H93: 6.387 | I93: NA | J93: NA | K93: NA | L93: combined | M93: pine forest;oak forest | N93: dominated by pine (P. pinaster) and oak (Q. suber, Q. ilex and Q. pubescens) | O93: none
A94: 280 | B94: 10 | C94: 1959 | E94: France | F94: exact | G94: 43.280796 | H94: 6.387 | I94: NA | J94: NA | K94: NA | L94: combined | M94: pine forest;oak forest | N94: dominated by pine (P. pinaster) and oak (Q. suber, Q. ilex and Q. pubescens) | O94: none
A95: 280 | B95: 11 | C95: 1959 | E95: France | F95: exact | G95: 43.280796 | H95: 6.387 | I95: NA | J95: NA | K95: NA | L95: combined | M95: pine forest;oak forest | N95: dominated by pine (P. pinaster) and oak (Q. suber, Q. ilex and Q. pubescens) | O95: none
... A122: 280 | B122: 38 | C122: 1962 | E122: France | F122: exact | G122: 43.280796 | H122: 6.387 | I122: NA | J122: NA | K122: NA | L122: combined | M122: pine forest;oak forest | N122: dominated by pine (P. pinaster) and oak (Q. suber, Q. ilex and Q. pubescens) | O122: none
A123: 280 | B123: 39 | C123: 1970 | E123: France | F123: exact | G123: 43.280796 | H123: 6.387 | I123: NA | J123: NA | K123: NA | L123: combined | M123: pine forest;oak forest | N123: dominated by pine (P. pinaster) and oak (Q. suber, Q. ilex and Q. pubescens) | O123: none
A124: 280 | B124: 40 | C124: 1970 | E124: France | F124: exact | G124: 43.280796 | H124: 6.387 | I124: NA | J124: NA | K124: NA | L124: combined | M124: pine forest;oak forest | N124: dominated by pine (P. pinaster) and oak (Q. suber, Q. ilex and Q. pubescens) | O124: none
A125: 280 | B125: 41 | C125: 1970 | E125: France | F125: exact | G125: 43.280796 | H125: 6.387 | I125: NA | J125: NA | K125: NA | L125: combined | M125: pine forest;oak forest | N125: dominated by pine (P. pinaster) and oak (Q. suber, Q. ilex and Q. pubescens) | O125: none
A126: 280 | B126: 42 | C126: 1970 | E126: France | F126: exact | G126: 43.280796 | H126: 6.387 | I126: NA | J126: NA | K126: NA | L126: combined | M126: pine forest;oak forest | N126: dominated by pine (P. pinaster) and oak (Q. suber, Q. ilex and Q. pubescens) | O126: none
...

Sheet 2_fire_resumen

Sheet 3_measures
A1: our_id | B1: response_variable | C1: response_units | D1: variable_type | E1: variable_subtype | F1: sampling_type | G1: measure_date | H1: season | I1: moderator_type | J1: comments
A2: 4 | B2: QMD (quadratic mean diameter) | C2: cm | D2: vegetation | E2: structure | F2: plot | G2: 2017_01_06 | I2: fire severity;drought probability
A3: 4 | B3: Stem density | C3: stems / ha | D3: vegetation | E3: regeneration | F3: plot | G3: 2017_01_06 | I3: fire severity;drought probability
A4: 4 | B4: Live canopy height | C4: m | D4: vegetation | E4: structure | F4: plot | G4: 2017_01_06 | I4: fire severity;drought probability
A5: 4 | B5: Stem mortality | C5: p. (0-1) | D5: vegetation | E5: regeneration | F5: plot | G5: 2017_01_06 | I5: fire severity;drought probability
A6: 4 | B6: Resprouting stems | C6: p. (0-1) | D6: vegetation | E6: regeneration | F6: plot | G6: 2017_01_06 | I6: fire severity;drought probability
A7: 4 | B7: Fine woody debris | C7: t / ha | D7: vegetation | E7: structure | F7: plot | G7: 2017_01_06 | I7: fire severity;drought probability
A8: 4 | B8: Stem diameter (DBH) | C8: cm | D8: vegetation | E8: structure | F8: plot | G8: 2017_01_06 | I8: fire severity;drought probability
A9: 4 | B9: Stem survival | C9: p. (0-1) | D9: vegetation | E9: regeneration | F9: plot | G9: 2017_01_06 | I9: fire severity;drought probability;tree species;tree cross-sectional area;stem size
A10: 16 | B10: NDVI | C10: -1 to +1 | D10: vegetation | E10: spectral response | F10: remote sensing | G10: 2017_09_28 | I10: gully morphology (width, plan area);topography (ruggeness index, altitude, slope, curvature, flow accumulation);fire severity;time | J10: spectral response refered to regeneration
A11: 17 | B11: sediment yield | C11: Mg / ha · year | D11: soil | E11: erosion | F11: plots | G11: 2016_06 | I11: se_management type;ground cover;precipitation (depth, intensity);canopy closure;time
A12: 17 | B12: ground cover | C12: % | D12: vegetation | E12: structure | F12: plots | G12: 2016_06 | I12: se_management type;time | J12: also could be soil subtype because groundcover classes are: bare soil, wood, vegetation
A13: 17 | B13: canopy closure | C13: % | D13: vegetation | E13: structure | F13: plots | G13: 2016_06 | I13: se_management type;time
A14: 17 | B14: bulk density | C14: g / cm3 | D14: soil | E14: physical properties | F14: plots | G14: 2016_06 | I14: soil depth;se_management type;time
A15: 17 | B15: Hydraulic conductivity (Kfs) | C15: mm / hr | D15: soil | E15: physical properties | F15: plots | G15: 2016_06 | I15: se_management type;time
A16: 17 | B16: soil water repellency | C16: s | D16: soil | E16: physical properties | F16: plots | G16: 2016_06 | I16: se_management type;time
A17: 29 | B17: species composition | C17: nº species | D17: vegetation | E17: composition | F17: transects | G17: 1994_07 | I17: NA
A18: 29 | B18: reproductive strategy | C18: G, R | D18: vegetation | E18: composition | F18: transects | G18: 1994_07 | I18: NA
A19: 29 | B19: height class | C19: % | D19: vegetation | E19: regeneration | F19: transects | G19: 1994_07 | I19: fire intensity
A20: 29 | B20: Height class | C20: cm | D20: vegetation | E20: structure | F20: transects | G20: 1994_07 | I20: fire intensity
A21: 29 | B21: recovery of soil cover | C21: % | D21: vegetation | E21: structure | F21: transects | G21: 1994_07 | I21: fire intensity
A22: 78 | B22: diversity (Berger-Parker index) | C22: 0-5 | D22: vegetation | E22: diversity | F22: plots;transects | G22: 1990_09 | I22: soil type;time
A23: 78 | B23: eveness(Camargo's index) | C23: 0-1 | D23: vegetation | E23: diversity | F23: plots;transects | G23: 1990_09 | I23: soil type;time
A24: 78 | B24: relative abundance | C24: nº individuals | D24: vegetation | E24: composition | F24: plots;transects | G24: 1990_09 | I24: soil type;time;species rank
A25: 84 | B25: multifunctionality | C25: 0-1,25 | D25: others | E25: ecosystem services | F25: plots;transects | G25: 1978 | I25: fire recurrence;TSLF (time since long fire)
A26: 84 | B26: biodiversity conservation | C26: 0-1,25 | D26: others | E26: ecosystem services | F26: plots;transects | G26: 1978 | I26: fire recurrence;TSLF (time since long fire) | J26: ecosystem service of suport
A27: 84 | B27: food production | C27: 0-1,25 | D27: others | E27: ecosystem services | F27: plots;transects | G27: 1978 | I27: fire recurrence;TSLF (time since long fire) | J27: ecosystem service of provision
A28: 84 | B28: carbon sequestration | C28: 0-1,25 | D28: others | E28: ecosystem services | F28: plots;transects | G28: 1978 | I28: fire recurrence;TSLF (time since long fire) | J28: ecosystem service of regulation
A29: 84 | B29: disturbance regulation | C29: 0-1,25 | D29: others | E29: ecosystem services | F29: plots;transects | G29: 1978 | I29: fire recurrence;TSLF (time since long fire) | J29: ecosystem service of regulation
A30: 84 | B30: supporting services | C30: 0-1,25 | D30: others | E30: ecosystem services | F30: plots;transects | G30: 1978 | I30: fire recurrence;TSLF (time since long fire) | J30: ecosystem service of suport
A31: 84 | B31: dead fuel bulk density | C31: 0-1,3 | D31: soil | E31: physical properties | F31: plots;transects | G31: 1978 | I31: fire recurrence
A32: 103 | B32: snag basal diameter | C32: cm | D32: vegetation | E32: structure | F32: plots;subplots | G32: 2006_02 | I32: s_management type;elevation;
A33: 103 | B33: snag fall rate | C33: % | D33: vegetation | E33: ecological processes | F33: plots;subplots | G33: 2006_02 | I33: s_management type;time
A34: 103 | B34: snag retention time | C34: days | D34: vegetation | E34: ecological processes | F34: plots;subplots | G34: 2006_02 | I34: silvicultural treatment;elevation;snag basal diameter
A35: 111 | B35: waste decomposition | C35: 0-1 | D35: others | E35: ecosystem services | F35: plots;transects;grid squares | G35: 2012_10 | I35: e_management type;soil properties;species richness;ground cover;time | J35: ecosystem service of suport
A36: 111 | B36: water cycle | C36: 0-1 | D36: others | E36: ecosystem services | F36: plots;transects;grid squares | G36: 2012_10 | I36: e_management type;soil properties;species richness;ground cover;time | J36: ecosystem service of suport
A37: 111 | B37: nutrient cycling | C37: 0-1 | D37: others | E37: ecosystem services | F37: plots;transects;grid squares | G37: 2012_10 | I37: e_management type;soil properties;species richness;ground cover;time | J37: ecosystem service of suport
A38: 111 | B38: climate regulation | C38: 0-1 | D38: others | E38: ecosystem services | F38: plots;transects;grid squares | G38: 2012_10 | I38: e_management type;soil properties;species richness;ground cover;time | J38: ecosystem service of regulation
A39: 111 | B39: biomass production | C39: 0-1 | D39: others | E39: ecosystem services | F39: plots;transects;grid squares | G39: 2012_10 | I39: e_management type;soil properties;species richness;ground cover;time | J39: ecosystem service of provision
A40: 111 | B40: multifunctionality | C40: 0-1 | D40: others | E40: ecosystem services | F40: plots;transects;grid squares | G40: 2012_10 | I40: e_management type;soil properties;species richness;ground cover;time
A41: 142 | B41: diversity (Shannon index) | C41: % | D41: vegetation | E41: diversity | F41: plots | G41: 1999_07 | I41: site;s_management type
A42: 142 | B42: total average cover | C42: % | D42: vegetation | E42: structure | F42: plots | G42: 1999_07 | I42: site;s_management type
A43: 142 | B43: shrub richness | C43: nº species | D43: vegetation | E43: diversity | F43: plots | G43: 1999_07 | I43: site;s_management type
A44: 142 | B44: macrolichens (IAP index) | C44: 0-3,5 | D44: vegetation | E44: diversity | F44: plots | G44: 1999_07 | I44: site;s_management type;fire recurrence
A45: 142 | B45: dead wood cover (TDWC index) | C45: % | D45: vegetation | E45: structure | F45: plots | G45: 1999_07 | I45: site;s_management type;fire recurrence
A46: 142 | B46: ground cover index (GC) | C46: % | D46: vegetation | E46: structure | F46: plots | G46: 1999_07 | I46: site;s_management type | J46: also could be soil subtype because groundcover classes are: bare soil, stone, organic matter, moss or lichen, ferns, herbaceous plants and shrubs
A47: 142 | B47: macrolichens (SEF index) | C47: 0-10 | D47: vegetation | E47: diversity | F47: plots | G47: 1999_07 | I47: site;s_management type
A48: 145 | B48: vegetation cover | C48: % | D48: vegetation | E48: structure | F48: plots;transects | G48: 2005_06 | I48: regeneration mode;time;Raunkiaer's life form
A49: 145 | B49: species richness | C49: nº species | D49: vegetation | E49: diversity | F49: plots;transects | G49: 2005_06 | I49: NA
A50: 152 | B50: Land cover change | C50: % | D50: vegetation | E50: spectral response | F50: remote sensing | G50: 1956 | I50: time; species; DBH | J50: spectral response refered to regeneration
A51: 152 | B51: Nº of trees | C51: nº individuals | D51: vegetation | E51: structure | F51: remote sensing | G51: 1956 | I51: species; DBH
A52: 152 | B52: timber volume | C52: % | D52: vegetation | E52: structure | F52: remote sensing | G52: 1956 | I52: time; species
A53: 168 | B53: NDVI | C53: -1 to +1 | D53: vegetation | E53: spectral response | F53: remote sensing | G53: 1997_07_25 | I53: time;NBR | J53: spectral response refered to regeneration
A54: 177 | B54: richness | C54: nº species | D54: vegetation | E54: diversity | F54: plots;transects | G54: 1991_03 | I54: year;s_management type
A55: 177 | B55: vegetation cover | C55: % | D55: vegetation | E55: structure | F55: plots;transects | G55: 1991_03 | I55: year;s_management type
A56: 177 | B56: pine seedling growth | C56: % | D56: vegetation | E56: structure | F56: plots;transects | G56: 1991_03 | I56: year;s_management type
A57: 177 | B57: pine seedling mortality | C57: % | D57: vegetation | E57: ecological processes | F57: plots;transects | G57: 1991_03 | I57: year;s_management type
A58: 177 | B58: pine seedling production | C58: % | D58: vegetation | E58: ecological processes | F58: plots;transects | G58: 1991_03 | I58: year;s_management type
A59: 177 | B59: species cover | C59: % | D59: vegetation | E59: composition | F59: plots;transects | G59: 1991_03 | I59: year;s_management type
A60: 177 | B60: seeder species relative abundance | C60: nº species / plot | D60: vegetation | E60: composition | F60: plots;transects | G60: 1991_03 | I60: year;s_management type | J60: plot is 4900 m2
A61: 187 | B61: runoff | C61: mm; % | D61: soil | E61: erosion | F61: plots | G61: 1989_10_10 | I61: rainfall intensity;vegetation cover;slope;soil exposure;fire intensity
A62: 187 | B62: sediment yield | C62: g / m2 | D62: soil | E62: erosion | F62: plots | G62: 1989_10_10 | I62: rainfall intensity;vegetation cover;slope;soil exposure;fire intensity
A63: 190 | B63: NDVI | C63: -1 to +1 | D63: vegetation | E63: spectral response | F63: remote sensing | G63: 1984 | I63: time | J63: spectral response refered to regeneration
A64: 200 | B64: pine seedling growth | C64: % | D64: vegetation | E64: structure | F64: plots | G64: 1995_02 | I64: time;s_management type
A65: 200 | B65: pine seedling mortality | C65: % | D65: vegetation | E65: ecological processes | F65: plots | G65: 1995_02 | I65: time;s_management type
A66: 200 | B66: pine seedling height | C66: cm | D66: vegetation | E66: structure | F66: plots | G66: 1995_02 | I66: time;s_management type
A67: 200 | B67: pine seedling density | C67: individuals / m2 | D67: vegetation | E67: regeneration | F67: plots | G67: 1995_02 | I67: time;s_management type
A68: 200 | B68: seedling emergence | C68: % | D68: vegetation | E68: regeneration | F68: plots | G68: 1995_02 | I68: time;s_management type
A69: 200 | B69: average frequency of height classes | C69: % | D69: vegetation | E69: structure | F69: plots | G69: 1995_02 | I69: time;s_management type
A70: 200 | B70: survival probability | C70: p. (0-1) | D70: vegetation | E70: ecological processes | F70: plots | G70: 1995_02 | I70: time;s_management type;height class
A71: 208 | B71: vegetation cover | C71: % | D71: vegetation | E71: structure | F71: plots | G71: 2001_04 | I71: site;exposure
A72: 208 | B72: floristic similarity (Sorensen index) | C72: % | D72: vegetation | E72: diversity | F72: plots | G72: 2001_04 | I72: site;exposure
A73: 208 | B73: richness | C73: nº species | D73: vegetation | E73: diversity | F73: plots | G73: 2001_04 | I73: site;exposure
A74: 208 | B74: diversity (Shannon index) | C74: 1,4-2,7 | D74: vegetation | E74: diversity | F74: plots | G74: 2001_04 | I74: site;exposure
A75: 208 | B75: eveness | C75: p. (0-1) | D75: vegetation | E75: diversity | F75: plots | G75: 2001_04 | I75: site;exposure
... A79: 215 | B79: survival | C79: p. (0-1) | D79: vegetation | E79: ecological processes | F79: plot | G79: 2005_10 | I79: site;r_management type;specie;time
A80: 222 | B80: EVI index single fires | C80: p. (0-1) | D80: vegetation | E80: spectral response | F80: remote sensing | G80: 1985_08_8 | I80: aspect;year;site | J80: spectral response refered to regeneration
A81: 222 | B81: EVI index repeated fires | C81: p. (0-1) | D81: vegetation | E81: spectral response | F81: remote sensing | G81: 1985_08_8 | I81: aspect;nº times burnt;site | J81: spectral response refered to regeneration
A82: 240 | B82: Basal area increment (BAI) | C82: mm2 / y | D82: vegetation | E82: structure | F82: tree ring measurements | G82: 2021_03 | I82: postfire time
A83: 240 | B83: Intra-annual density fluctuations (IASDF) | C83: p. (0-1) | D83: vegetation | E83: structure | F83: tree ring measurements | G83: 2021_03 | I83: postfire time
A84: 240 | B84: 13C | C84: 0/00 | D84: vegetation | E84: biological properties | F84: tree ring measurements | G84: 2021_03 | I84: NA
A85: 240 | B85: 18O | C85: 0/00 | D85: vegetation | E85: biological properties | F85: tree ring measurements | G85: 2021_03 | I85: NA
A86: 240 | B86: Xilogenesis | C86: nº cells | D86: vegetation | E86: structure | F86: tree ring measurements | G86: 2021_03 | I86: NA
A87: 245 | B87: survival | C87: % | D87: vegetation | E87: ecological processes | F87: grid;transects | G87: 2003_12 | I87: plant status (resprout or planted);specie
A88: 245 | B88: height | C88: cm | D88: vegetation | E88: structure | F88: grid;transects | G88: 2003_12 | I88: plant status (resprout or planted);specie
A89: 245 | B89: diameter | C89: cm | D89: vegetation | E89: structure | F89: grid;transects | G89: 2003_12 | I89: plant status (resprout or planted);specie
A90: 266 | B90: pine regeneration density | C90: individuals / m2 | D90: vegetation | E90: regeneration | F90: plots;quadrants | G90: 2002 | I90: soil branches;previous land use;topographic position;distance to unburned woodlands;bedrock type
A91: 270 | B91: pine density | C91: pines / ha | D91: vegetation | E91: regeneration | F91: transects;tree ring measurements | G91: 2004 | I91: fire recurrence
A92: 270 | B92: pine height | C92: cm | D92: vegetation | E92: structure | F92: transects;tree ring measurements | G92: 2004 | I92: fire recurrence
A93: 270 | B93: pine diameter | C93: mm | D93: vegetation | E93: structure | F93: transects;tree ring measurements | G93: 2004 | I93: fire recurrence
... A95: 270 | B95: pine time of recruitment | C95: year | D95: vegetation | E95: regeneration | F95: transects;tree ring measurements | G95: 2004 | I95: NA
A96: 271 | B96: reproductive pines | C96: % | D96: vegetation | E96: regeneration | F96: plots | G96: 2003 | H96: spring | I96: regeneration age;s_management type
A97: 271 | B97: pine new cones produced | C97: cones / pine | D97: vegetation | E97: regeneration | F97: plots | G97: 2003 | H97: spring | I97: regeneration age;s_management type
A98: 271 | B98: pine new cones - open cones | C98: cones / pine | D98: vegetation | E98: regeneration | F98: plots | G98: 2003 | H98: spring | I98: regeneration age;s_management type
A99: 271 | B99: pine mature cones | C99: cones / pine | D99: vegetation | E99: regeneration | F99: plots | G99: 2003 | H99: spring | I99: regeneration age;s_management type
A100: 271 | B100: pine inmature cones | C100: cones / pine | D100: vegetation | E100: regeneration | F100: plots | G100: 2003 | H100: spring | I100: regeneration age;s_management type
A101: 280 | B101: oak recruitment | C101: individuals / 100 m2 | D101: vegetation | E101: regeneration | F101: plots | G101: 2008_03 | I101: vegetation type;fire recurrence
A102: 282 | B102: survival | C102: % | D102: vegetation | E102: ecological processes | F102: plots | G102: 2003_12 | I102: NA
A103: 282 | B103: mortality | C103: % | D103: vegetation | E103: ecological processes | F103: plots | G103: 2003_12 | I103: NA
A104: 282 | B104: broadleaves mortality | C104: % | D104: vegetation | E104: ecological processes | F104: plots | G104: 2003_12 | I104: specie
...

Sheet 3_measures_resumen
A1: Tipo de variable respuesta | B1: Recuento | C1: % | I1: moderator_type | J1: n_papers | K1: Moderator group | O1: Big groups | P1: subtypes
A2: vegetación | B2: =COUNTIF('3_measures'!D:D, "vegetation") -> 955 | C2: =B2/$B$6 -> 0.47869674 | J2: 8 | O2: fire | P2: years after fire
A3: suelo | B3: =COUNTIF('3_measures'!D:D, "soil") -> 787 | C3: =B3/$B$6 -> 0.39448622 | I3: Basal Area Increment | J3: 1 | K3: vegetation | O3: vegetation
A4: fauna | B4: =COUNTIF('3_measures'!D:D, "fauna") -> 194 | C4: =B4/$B$6 -> 0.097243108 | I4: Fire type (crown vs. understory) | J4: 1 | K4: fire | O4: topography
A5: otras | B5: =COUNTIF('3_measures'!D:D, "others") -> 59 | C5: =B5/$B$6 -> 0.029573935 | I5: NBR disturbance | J5: 1 | K5: fire | O5: management
B6: =SUM(B2:B5) -> 1995 | C6: =B6/$B$6 -> 1 | I6: Regenerative functional traits | J6: 5 | K6: vegetation
I7: SOM | J7: 4
I8: Soil layer | J8: 5
I9: TOC | J9: 3
I10: Thornthwaite index | J10: 4
I11: VARI index | J11: 1
I12: annual herbs) | J12: 2
I13: aspect | J13: 14 | K13: topography
I14: aspects | J14: 2 | K14: topography
I15: available phosphorus | J15: 4
I16: bark thickness | J16: 1
I17: basal area of Pinus halepensis | J17: 1
I18: basal area of Quercus ilex | J18: 1
I19: basal area of Quercus pubescens | J19: 1
I20: burn severity | J20: 4
I21: burned area | J21: 1
I22: burned/unburned | J22: 2
I23: cone age | J23: 4
I24: cone type | J24: 4
I25: distance from the unburned age | J25: 1
I26: distance to closest reproductive tree | J26: 1
... I28: electrical conductivity | J28: 4
I29: elevation) | J29: 1 | K29: topography
I30: fire id | J30: 1 | K30: fire
I31: fire occurrence | J31: 4 | K31: fire
I32: fire plot type | J32: 10 | K32: fire
I33: fire recurrence | J33: 14 | K33: fire
I34: fire return interval | J34: 1 | K34: fire
I35: fire severity | J35: 21 | K35: fire
I36: fire type (crown vs surface) | J36: 3 | K36: fire
I37: forest area | J37: 1
I38: land slope | J38: 1
I39: land use | J39: 5
I40: landscape type | J40: 1
I41: life form (woody, perennial herbs | J41: 2
I42: management_type | J42: 11
I43: microbial community structure | J43: 1
I44: micronutrients | J44: 4
I45: number of neighboring traps | J45: 1
I46: nutrients | J46: 3
I47: organic carbon | J47: 4
I48: piled dead branches cover | J48: 3
... I52: plot | J52: 5
I53: post-fire treatment | J53: 9 | K53: fire
I54: postfire pine age | J54: 9 | K54: fire
I55: potencial pollutants | J55: 4
I56: prefire stand age | J56: 6 | K56: fire
I57: recovery index | J57: 1
I58: regeneration density | J58: 2
I59: regenerative trajectory | J59: 1
I60: sampling period | J60: 4
I61: season | J61: 10
I62: seed protection | J62: 2
I63: severity | J63: 1
I64: shrub cover classes | J64: 1
I65: site | J65: 15
I66: slope | J66: 9 | K66: topography
I67: soil color | J67: 2
I68: soil humidity | J68: 2
I69: species | J69: 2
I70: spread dead branches cover | J70: 3
I71: states of regeneration: | J71: 1
I72: temperature | J72: 1
I73: terrain roughness | J73: 1 | K73: topography
I74: time | J74: 12
I75: time after fire | J75: 45 | K75: fire
I76: time since fire | J76: 3 | K76: fire
I77: total basal area | J77: 1
I78: total nitrogen | J78: 4
I79: tree diameter | J79: 2
I80: tree status | J80: 2
I81: unburned forest area | J81: 1
I82: understory height | J82: 2
I83: vegetation cover | J83: 3
I84: vegetation recovery | J84: 1
I85: vegetation type | J85: 5
I86: woodland type | J86: 8
I87: year | J87: 7
I88: year after fire | J88: 1 | K88: fire
I89: years to recovery | J89: 1
I90: C factor | J90: 1
I91: CVH | J91: 1
I92: DBH | J92: 2
I93: Euclidean distance | J93: 4
I94: Fire ocurrence and moss presence (unburned, moss, bare) | J94: 18 | K94: fire
I95: Fire type | J95: 1 | K95: fire
I96: Functional group | J96: 1
I97: Gramineae | J97: 1
I98: HLI | J98: 1
I99: NA | J99: 62
I100: NBR regrowth | J100: 1 | K100: vegetation
I101: NDVI trend (15 yr post fire) | J101: 1 | K101: fire
I102: PCA (precipitation | J102: 1
I103: Postfire management treatment | J103: 9 | K103: fire
I104: Raunkiaer's life form | J104: 1
...

Sheet 4_Exclusion
A1: our_id | B1: reason | C1: comments | D1: excludetype
A2: 31 | B2: centered in remote sensing prediction models efficiency | D2: C4
A3: 36 | B3: book chapter | D3: C1
A4: 37 | B4: book chapter | D4: C1 | F4: recompte | G4: %
A5: 45 | B5: conference paper | D5: C1 | F5: =COUNTIF(D:D,"C1") -> 16 | G5: =F5/$F$10 -> 0.30769231
A6: 86 | B6: predictive models | D6: C4 | F6: =COUNTIF(D:D,"C2") -> 19 | G6: =F6/$F$10 -> 0.36538462
A7: 88 | B7: experiment in controlled conditions | D7: C4 | F7: =COUNTIF(D:D,"C3") -> 1 | G7: =F7/$F$10 -> 0.019230769
A8: 46 | B8: it does not present postfire responses, about diverse degradation factors | D8: C5 | F8: =COUNTIF(D:D,"C4") -> 14 | G8: =F8/$F$10 -> 0.26923077
A9: 108 | B9: it is in non mediterranean environment | D9: C3 | F9: =COUNTIF(D:D,"C5") -> 2 | G9: =F9/$F$10 -> 0.038461538
A10: 135 | B10: not a recovery context, measures in an stablished forest about sivicultural treatments | D10: C2 | F10: =SUM(F5:F9) -> 52
A11: 140 | B11: experiment in controlled conditions | D11: C4
A12: 163 | B12: centered in thinning effects, not postfire effects | D12: C2
A13: 181 | B13: book chapter | D13: C1
A14: 194 | B14: prescribed burning and response of a a grass | D14: C2
A15: 202 | B15: effects of waste compost treatment to burn soils | D15: C2
A16: 205 | B16: shrubby and herbaceus context, not forest | D16: C2
A17: 246 | B17: centered in quarry rehabilitations and no forest context | D17: C2
A18: 656 | B18: conference paper | D18: C1
A19: 693 | B19: proceedings paper | D19: C1
A20: 770 | B20: proceedings paper | D20: C1
A21: 998 | B21: conference paper | D21: C1
A22: 1019 | B22: proceedings paper | D22: C1
... A25: 279 | B25: it doesn't mention specific fires | D25: C5
A26: 84 | B26: Duda - incluye incendios experimentales aunque es minoria
A27: 307 | B27: Study conducted in an established Arbutus unedo forest, not in a recovery context | D27: C6
A28: 321 | B28: Predictive models and centered in evaluating remote sensing efficiency | D28: C4
A29: 341 | B29: centered in acorn productivity, not in postfire response. In an established recovered postfire forest | D29: C6
A30: 404 | B30: the 90% of the study area is scrubland | D30: C2
A31: 410 | B31: lacks specific fire past events and precise dates, more regional and broad scale
A32: 411 | B32: lacks specific fire past events and precise dates, more regional and broad scale
A33: 513 | B33: main vegetation is shrubland and agricultural, forest type is not distinguished in results | D33: C2
A34: 539 | B34: centered in management implications and not field work | D34: C2
A35: 568 | B35: it applies predictive models and machine learning algorithm to study postfire recovery | D35: C4
A36: 52 | B36: Duda - son parcelas quemadas, pero lo he registrado igual
A37: 666 | B37: palaeoecology but not centered in fires, it does not identify fire episodes | D37: C6
A38: 675 | B38: it applies random forest model to predict factor effects on vegetation recovery | D38: C4
A39: 737 | B39: same article as 724
A40: 746 | B40: Duda - articulo en italiano
A41: 843 | B41: The studied community consists of codominant shrublands and forests; results were not differentiated by vegetation type | D41: C2
A42: 957 | B42: Duda - articulo en francés
A43: 1068 | B43: it does not evaluate a wildfire | D43: C2
A44: 1078 | B44: Duda - no access available online, in french
A45: 1034 | B45: thesis book | D45: C1
A46: 1031 | B46: reviews postfire regeneration of pine studies, no metodology | D46: C4
A47: 914 | B47: Duda - no sé si la figura 3 es suficiente para considerar que se estudia regeneración
A48: 919 | B48: provides combined results for mixed forest and shrubland areas without differentiating by vegetation type | D48: C2
A49: 1021 | B49: Duda - articulo en francés
A50: 989 | B50: Duda - articulo en francés
A51: 1003 | B51: Non available online. Original text in german
A52: 60 | B52: Duda - articulo en francés
A53: 122 | B53: Mixed scrub-forest zone. It not distinguish results by vegetation type | D53: C2
A54: 149 | B54: A laboratory study under controlled conditions | D54: C4
A55: 214 | B55: It does not evaluate postfire mammals recovery | D55: C6
A56: 234 | B56: Duda - it simulates rainfall in the field. That's a controlled rainfall | C56: entra
A57: 358 | B57: Studies ectomycorrizal community under laboratory conditions | D57: C4
A58: 363 | B58: mediterranean shrubland study zone | D58: C2
A59: 1011 | B59: book chapter | D59: C1
A60: 878 | B60: centered in the efficiency of remote sensing tecnhique, not ecological responses | D60: C6
A61: 400 | B61: Duda - included, but previous to the fire in 2021 there were prescribed fires | C61: yo lo dejaria porque a pesar de la gestión preincendio cuando se dio el incendio seguía siendo un bosque
A62: 150 | B62: persistent shrubland area study zone | D62: C2
A63: 793 | B63: It test the use of UAVs for forest monitoring | D63: C6
A64: 796 | B64: it does not assess the response to fire, but rather analyzes the size-density dynamics of the stands that have already regenerated after the fire, with a greater focus on future management | D64: C6
A65: 534 | B65: Not available online
A66: 573 | B66: A laboratory study under controlled conditions | D66: C4
A67: 579 | B67: Not available online
A68: 134 | B68: It does not assess post-fire responses (criteria C4) but how early thinning affects Carbon storage in naturally regenerated aleppo pine after fire | C68: Casi segura que es exclusion, comentar para mas seguridad | D68: C6
A69: 185 | B69: It does not assess post-fire responses (criteria C4). Study about Mediterranean vegetation dynamics from palynological records. Mentioned fires as part of Mediterranean dynamics but do not assess fire resposnes to a specific fire | D69: C6
A70: 227 | B70: It does not specifically assess post-fire responses (criteria C4). "synthesis of palynological and microscopic charcoal results of eight radiocarbon-dated sequences of the Mediterranean region on the East Iberian Peninsula. The aim of this work is to improve our knowledge about the linkages between Holocene fire regime, climatic conditions, vegetation, and land-use history." | C70: Paleo. Revisar | D70: C6
A71: 235 | B71: Chile
A72: 326 | B72: The wildfire does not occur in the Mediterranean Basin (Australia)
A73: 356 | B73: Duda - Trabajo con 1000 parcelas de IFN sin coordenadas (ni rango, ni exactas… no se pueden extraer). Tampoco hay datos de los incendios
A74: 385 | B74: Responses are not based in field data | D74: C4
A75: 503 | B75: laboratory experiment | D75: C4
A76: 542 | B76: en uno de los incendios hay fuego prescrito, y lo excluyo, incluyendo el incendio tanto en bosque como maturral | D76: C2
A77: 554 | B77: no se centra en un unico incendios sino en una ara bastante afectada por incendio y estudia el tiempo desde el ultimo incendio pero no da información especifica
A78: 394 | B78: shrubby and herbaceus context (garrige), not forest | D78: C2
A79: 366 | B79: experimental fires over Mediterranean-shrub ecosystem | D79: C2
A80: 331 | B80: Chile
A81: 201 | B81: book chapter | D81: C1
A82: 901 | B82: conference paper | D82: C1
A83: 1010 | B83: Duda - artículo en francés
A84: 691 | B84: capitulo de libro | D84: C1
A85: 792 | B85: Duda - no analiza exactamente el efecto de los incendios, sino la distribucion de especies a lo largo de gradientes de perturbacion, entre elos zonas urbanizadas, cultivos, y dos zonas que sgún dice han sido repetidamente incendiadas.
A86: 494 | B86: shrubland | D86: C2
A87: 994 | B87: experimental conditions | D87: C4

Sheet Aux
A1: study_type | B1: study_level | C1: origin_coords | D1: severity | E1: postfire_management | F1: fire_type | G1: variable_type | H1: variable_subtype | J1: Apuntes
A2: remote sensing | B2: species | C2: exact | D2: low | E2: silvicultural | F2: single | G2: vegetation | H2: diversity
A3: palaeoecology | B3: community | C3: mean point | D3: moderate | E3: reforestation | F3: combined | G3: soil | H3: composition | J3: Abundancia total | K3: Nº individuos totales de la especie. Indica estructura de la comunidad.
A4: field | B4: community;species | C4: estimated | D4: high | E4: erosion control | G4: fauna | H4: structure | J4: Abundancia relativa | K4: proporción de una especie o taxón respecto a todas las especies o taxones contenidos en un sitio. Indica que tan común o rara es la especie en la comunidad. Es una variable de composición
A5: field;remote sensing | B5: NA | D5: low;moderate | E5: none | G5: others | H5: regeneration | J5: Eveness index | K5: Species evenness describes the commonness or rarity of a species; it requires knowing the abundance of each species relative to those of the other species within the community.
A6: others | D6: moderate;high | E6: silvicultural;erosion control | H6: physical properties
D7: low;high | E7: erosion control; reforestation | H7: chemical properties
D8: all | E8: silvicultural; reforestation | H8: biological properties
D9: NA | E9: amendments | H9: ecological processes
E10: silvicultural;erosion control;reforestation | H10: erosion
E11: silvicultural;amendments | H11: interactions
E12: NA | H12: reproduction
E13: herbivore exclusion | H13: spectral response
E14: silvicultural;none | H14: others
H15: landscape
H16: ecosystem services | I16: *for ecosystem services, in comments
H17: supporting services
H18: provisioning services
H19: regulating services
H20: cultural services
H21: functional traits
